{
  "category": "후원 및 기부",
  "subcategory": "착한가게",
  "title": "착한가게",
  "url": "https://www.saha.go.kr/portal/contents.do?mId=0508030000",
  "mId": "0508030000",
  "type": "page",
  "content": "착한가게\n행복이 착! 착! 착! 여러분의 가게에 행복을 드리겠습니다.  함께 해주시면   착한가게 현판 을 보내드립니다.\n착한가게란?\n착한가게현황\n매월 3만원 이상, 매출의 일정액을 어려운 이웃들에게 나누는 가게\n자영업자 또는 중소기업, 프랜차이즈, 학원, 병원 등 모든 업종 참여 가능\n착한가게가 되면 어떤 혜택이 있나요?\n착한가게 인증 현판 발송·부착\n기부금 영수증 발행 및 소득세법·법인세법에 의한 세제혜택\n다양한 홍보 : 사랑의열매 홈페이지, 정기간행물, SNS 채널 등\n착한가게가 기부금은 어디에 쓰이나요?\n저소득 가정의 생계비 및 의료비, 위기가정지원 사업에 활용\n기부금을 적립하여 저소득 취약계층을 대상으로 맞춤형 복지서비스를 제공하는 “사하 희망두레박사업”에 활용\n기부 문의\n사하구 복지정책과 복지자원계 (☏220-5174)\n2025년 사하 희망두레박사업\n① 저장강박 세대의 주거환경 개선사업  “이웃사촌플러스”\n② 주거취약계층의 주민주도형 주거복지사업  “구해줘 홈즈”\n③ 학교밖 청소년의 사회적응력 향상 지원사업  “3GO”\n④ 사회적 고립 및 취약계층 결식 예방사업  “건강+반찬 지원사업”\n⑤ 저소득 1인 가구 물품 지원사업  “네 계절을 함께할게”\n⑥ 범죄 피해 아동의 심리 회복사업  “함께 위로하다, 함께 성장하다”\n⑦ 복지사각지대 발굴 및 지원체계 구축사업  “이웃의 재발견”\n⑧ 정책이주지 돌봄사각지대 아동 지원사업  “장림1동 마을품 모둠사업”",
  "attachments": [
    {
      "name": "착한가게+현황(2024.12기준)게시용.xlsx",
      "url": "https://www.saha.go.kr/cmm/fms/FileDown.do?atchFileId=FILE_000000000179551&fileSn=0",
      "saved_path": "data/후원_및_기부/attachments/0508030000/착한가게+현황(2024.12기준)게시용.xlsx",
      "content": "[시트명] 착한가게-희망두레박\n연번 | 기부자명 | 동명 | 우편번호 | 주소\n1 | 괴정병원장례식장 | 괴정1동 | 49380 | 부산광역시 사하구 낙동대로249번길 11 (괴정동)\n2 | 금산인산농산물 | 괴정1동 | 49383 | 부산광역시 사하구 사하로185번길 35-11 (괴정동)\n3 | 남경 | 괴정1동 | 49388 | 부산광역시 사하구 괴정로 282 (괴정동)\n4 | 사하한의원 | 괴정1동 | 49384 | 부산광역시 사하구 괴정로 259 (괴정동)\n5 | 새부산약국 | 괴정1동 | 49340 | 부산광역시 사하구 낙동대로 230 (괴정동, 수민빌딩)\n6 | 이마트24부산괴정점 | 괴정1동 | 49381 | 부산광역시 사하구 사하로197번길 15, 삼부로얄 101호 (괴정동)\n7 | 이정윤성형외과의원 | 괴정1동 | 49381 | 부산광역시 사하구 낙동대로 231 (괴정동)\n8 | 전복나라 | 괴정1동 | 49383 | 부산광역시 사하구 괴정로 279 (괴정동)\n9 | 한빛약국 | 괴정3동 | 49339 | 부산광역시 사하구 낙동대로 158 (괴정동)\n10 | 대선약국 | 괴정3동 | 49355 | 부산광역시 사하구 낙동대로 213 (괴정동)\n11 | 유성약국 | 괴정3동 | 49350 | 부산광역시 사하구 낙동대로199번길 3 (괴정동)\n12 | 부영약국 | 괴정4동 | 49399 | 부산광역시 사하구 낙동대로 325, 1층 (괴정동)\n13 | 김기철치과의원 | 당리동 | 49328 | 부산광역시 사하구 낙동대로 398 (당리동)\n14 | 예림기획 | 당리동 | 49328 | 부산광역시 사하구 낙동대로398번길 14 (당리동)\n15 | 어부네코다리 | 당리동 | 49328 | 부산광역시 사하구 낙동대로 394-7, 1층 (당리동)\n16 | 허재영내과의원 | 당리동 | 49323 | 부산광역시 사하구 제석로 54 (당리동)\n17 | (주)영진종합전기 | 하단1동 | 49425 | 부산광역시 사하구 낙동남로 1358 (하단동)\n18 | 가야약국 | 하단1동 | 49430 | 부산광역시 사하구 하신번영로 233, 가락타운 2단지상가 227-107 (하단동)\n19 | 경진이앤지 | 하단1동 | 49409 | 부산광역시 사하구 낙동대로457번길 29 (하단동)\n20 | 박성욱피부과 | 하단1동 | 49427 | 부산광역시 사하구 낙동남로 1424, 6층 (하단동, 동원빌딩)\n21 | 오거리약국 | 하단1동 | 49408 | 부산광역시 사하구 낙동대로 449 (하단동)\n22 | 조경숙가정의학과소아과 | 하단1동 | 49414 | 부산광역시 사하구 하신중앙로 300-1 (하단동)\n23 | 하나로약국 | 하단1동 | 49427 | 부산광역시 사하구 낙동남로 1408 (하단동)\n24 | (주)사오건설 | 하단2동 | 49425 | 부산광역시 사하구 낙동남로 1348-1 (하단동)\n25 | (주)아트몰링 | 하단2동 | 49311 | 부산광역시 사하구 낙동남로 1413, 16층 통합사무소 (하단동, 아트몰링)\n26 | 동아기획 | 하단2동 | 49324 | 부산광역시 사하구 낙동대로 536 (하단동)\n27 | 본가사하점 | 하단2동 | 49301 | 부산광역시 사하구 하신번영로 403, B동 (하단동)\n28 | 제일돌곱창 | 하단2동 | 49308 | 부산광역시 사하구 낙동대로535번길 4 (하단동)\n29 | 대성약국 | 신평1동 | 49442 | 부산광역시 사하구 장평로 298 (신평동)\n30 | 전성업치과의원 | 신평1동 | 49418 | 부산광역시 사하구 장평로 299 (신평동)\n31 | 김사웅내과의원 | 신평2동 | 49431 | 부산광역시 사하구 하신번영로 199  (신평동)\n32 | 박상조소아청소년과의원 | 신평2동 | 49419 | 부산광역시 사하구 하신중앙로 184 (신평동)\n33 | 신익약국 | 신평2동 | 49419 | 부산광역시 사하구 하신중앙로 184 (신평동)\n34 | (주)대영정기 | 장림1동 | 49478 | 부산광역시 사하구 다산로 227 (장림동)\n35 | BJ TECH | 장림1동 | 49478 | 부산광역시 사하구 다산로225번길 45(장림동)\n36 | 부산장림표면처리사업협동조합 | 장림1동 | 49478 | 부산광역시 사하구 다산로 255 (장림동)\n37 | 성진종합상사 | 장림1동 | 49476 | 부산광역시 사하구 하신중앙로 40 (장림동)\n38 | 세화산업 | 장림1동 | 49478 | 부산광역시 사하구 다산로226번길 28 (장림동)\n39 | 우석치과의원 | 장림1동 | 49482 | 부산광역시 사하구 장림번영로 38-1, 4층 (장림동)\n40 | 장림연합의원 | 장림1동 | 49476 | 부산광역시 사하구 하신중앙로22번길 9 (장림동, 만리포빌딩 1층)\n41 | 천호카 | 장림1동 | 49476 | 부산광역시 사하구 하신중앙로 6 (장림동)\n42 | 비앤지1급종합정비 | 장림2동 | 49458 | 부산광역시 사하구 장림로 314 (장림동)\n43 | 이치과의원 | 장림2동 | 49509 | 부산광역시 사하구 다대로 247 (장림동)\n44 | 장약국 | 장림2동 | 49511 | 부산광역시 사하구 다대로 325 (장림동)\n45 | 건강왕약국 | 다대1동 | 49524 | 부산시 사하구 다대로 547, 1층 (다대동, 윤영빌딩)\n46 | 다대치과(손기찬) | 다대1동 | 49494 | 부산광역시 사하구 다대로 556, 5층 (다대동)\n47 | 라파요양병원 | 다대1동 | 49493 | 부산광역시 사하구 다대로 544, 진요빌딩 3~4층 (다대동)\n48 | 박상희내과의원 | 다대1동 | 49524 | 부산광역시 사하구 다대로 555 (다대동)\n49 | 백두봉삼계탕(양명화) | 다대1동 | 49505 | 부산광역시 사하구 다대로 714-1 (다대동)\n50 | 선안요양병원 | 다대1동 | 49503 | 부산광역시 사하구 다대로 616 (다대동)\n51 | 이화약국 | 다대1동 | 49505 | 부산광역시 사하구 다대낙조1길 19 (다대동)\n52 | 도원보쌈 | 다대2동 | 49521 | 부산광역시 사하구 다송로72번길 41 (다대동)\n53 | 캘리포니아치과 | 다대2동 | 49518 | 부산광역시 사하구 다대로429번길 5, 302호 (다대동)\n54 | 구평남해횟집 | 구평동 | 49456 | 부산광역시 사하구 을숙도대로748번길 3 (구평동)\n55 | 부산갈매기식당 | 구평동 | 49454 | 부산광역시 사하구 감천항로 185 (구평동)\n56 | 남해횟집 | 남포동 | 48983 | 부산광역시 중구 자갈치로48번길 3, 자갈치시장(남포동5가)\n57 | (주)큐엔큐 | 화전동 | 46738 | 부산광역시 강서구 화전산단3로 58 (화전동)\n58 | 우리약국 | 거제시 | 53286 | 경상남도 거제시 거제면 읍내로2길 28 (서상리, 거제종합시장)\n59 | 우리동네호두과자 | 당리동 | 49328 | 부산광역시 사하구 낙동대로410번길 14, 1층 104호(당리동)\n60 | 연일자동차정비공업사 | 구평동 | 49396 | 부산광역시 사하구 을숙도대로 755번길 1\n61 | 봉구비어(괴정점) | 괴정1동 | 49380 | 부산광역시 사하구 낙동대로 233번길 8\n62 | 최은석치과의원 | 신평2동 | 49431 | 부산광역시 사하구 하신번영로201번길 1 (신평동)\n[시트명] 착한가게-일반, 지정성금\n연번 | 기부자명 | 동명 | 우편번호 | 주소 | 비고 | 후원종료\n1 | GS25괴정뉴코아 | 괴정1동 | 49381 | 부산광역시 사하구 사하로 199-1 (괴정동) | 일반\n2 | 지오공인중개사 | 괴정3동 | 49351 | 부산광역시 사하구 사리로7번길 22 (괴정동)\n3 | 괴정중앙점현대자동차 | 괴정3동 | 49360 | 부산광역시 사하구 사하로 152 (괴정동)\n4 | 한우사랑 | 당리동 | 49328 | 부산광역시 사하구 낙동대로410번길 24 (당리동)\n5 | GS25당리행운점 | 당리동 | 49326 | 부산광역시 사하구 낙동대로450번길 2 (당리동)\n6 | GS25본병원점 | 당리동 | 49326 | 부산광역시 사하구 승학로 8 (당리동)\n7 | GS25가락타운점(최영옥) | 하단1동 | 49428 | 부산광역시 사하구 동매로 9 (하단동)\n8 | GS25하단사하점 | 하단1동 | 49427 | 부산광역시 사하구 하신중앙로 335 (하단동, 화경빌딩)\n9 | 더블루공인중개사무소 | 하단2동 | 49325 | 부산광역시 사하구 낙동대로 484 (하단동)\n10 | 신평점현대자동차 | 신평2동 | 49437 | 부산광역시 사하구 하신중앙로 118 (신평동)\n11 | 리클라인(이연환) | 장림1동 | 49478 | 부산광역시 사하구 다산로226번길 30 (장림동)\n12 | 오토오아시스롯데마트사하점 | 장림1동 | 49472 | 부산광역시 사하구 을숙도대로 610, 3층 (장림동, 롯데마트)\n13 | GS25감천유림점 | 감천1동 | 49445 | 부산광역시 사하구 감천로 46 (감천동)\n14 | 환성물회 | 신평2동 | 49431 | 부산광역시 사하구 하신번영로167번길 26, 2층 (신평동) | 지정\n15 | 장어나라장수마을 | 신평1동 | 49441 | 부산광역시 사하구 다대로142번길 60(신평동) | 지정\n16 | 피자덕 괴정점 | 괴정1동 | 49385 | 부산광역시 사하구 괴정로 230(괴정동) | 지정\n17 | 골드헤어 | 괴정1동 | 49379 | 부산광역시 사하구 장평로450번길 71(괴정동) | 일반\n18 | Midamoa Jewelry | 범천동 | 47365 | 부산광역시 부산진구 범일로142번길 7(범천동) | 일반\n19 | GS25괴정크로바점 | 괴정1동 | 49360 | 부산광역시 사하구 사하로 166   (괴정동)\n20 | 경신브레이크(신평점) | 신평1동 | 49439 | 부산 사하구 을숙도대로 581 (신평동) 신동아정비내 경신브레이크\n21 | 매듭쟁이 단홍 | 감천2동 | 49364 | 부산 사하구 감내1로175번길 101 (감천동) 단홍 1층"
    }
  ],
  "search_text": "착한가게\n행복이 착! 착! 착! 여러분의 가게에 행복을 드리겠습니다.  함께 해주시면   착한가게 현판 을 보내드립니다.\n착한가게란?\n착한가게현황\n매월 3만원 이상, 매출의 일정액을 어려운 이웃들에게 나누는 가게\n자영업자 또는 중소기업, 프랜차이즈, 학원, 병원 등 모든 업종 참여 가능\n착한가게가 되면 어떤 혜택이 있나요?\n착한가게 인증 현판 발송·부착\n기부금 영수증 발행 및 소득세법·법인세법에 의한 세제혜택\n다양한 홍보 : 사랑의열매 홈페이지, 정기간행물, SNS 채널 등\n착한가게가 기부금은 어디에 쓰이나요?\n저소득 가정의 생계비 및 의료비, 위기가정지원 사업에 활용\n기부금을 적립하여 저소득 취약계층을 대상으로 맞춤형 복지서비스를 제공하는 “사하 희망두레박사업”에 활용\n기부 문의\n사하구 복지정책과 복지자원계 (☏220-5174)\n2025년 사하 희망두레박사업\n① 저장강박 세대의 주거환경 개선사업  “이웃사촌플러스”\n② 주거취약계층의 주민주도형 주거복지사업  “구해줘 홈즈”\n③ 학교밖 청소년의 사회적응력 향상 지원사업  “3GO”\n④ 사회적 고립 및 취약계층 결식 예방사업  “건강+반찬 지원사업”\n⑤ 저소득 1인 가구 물품 지원사업  “네 계절을 함께할게”\n⑥ 범죄 피해 아동의 심리 회복사업  “함께 위로하다, 함께 성장하다”\n⑦ 복지사각지대 발굴 및 지원체계 구축사업  “이웃의 재발견”\n⑧ 정책이주지 돌봄사각지대 아동 지원사업  “장림1동 마을품 모둠사업”\n\n[시트명] 착한가게-희망두레박\n연번 | 기부자명 | 동명 | 우편번호 | 주소\n1 | 괴정병원장례식장 | 괴정1동 | 49380 | 부산광역시 사하구 낙동대로249번길 11 (괴정동)\n2 | 금산인산농산물 | 괴정1동 | 49383 | 부산광역시 사하구 사하로185번길 35-11 (괴정동)\n3 | 남경 | 괴정1동 | 49388 | 부산광역시 사하구 괴정로 282 (괴정동)\n4 | 사하한의원 | 괴정1동 | 49384 | 부산광역시 사하구 괴정로 259 (괴정동)\n5 | 새부산약국 | 괴정1동 | 49340 | 부산광역시 사하구 낙동대로 230 (괴정동, 수민빌딩)\n6 | 이마트24부산괴정점 | 괴정1동 | 49381 | 부산광역시 사하구 사하로197번길 15, 삼부로얄 101호 (괴정동)\n7 | 이정윤성형외과의원 | 괴정1동 | 49381 | 부산광역시 사하구 낙동대로 231 (괴정동)\n8 | 전복나라 | 괴정1동 | 49383 | 부산광역시 사하구 괴정로 279 (괴정동)\n9 | 한빛약국 | 괴정3동 | 49339 | 부산광역시 사하구 낙동대로 158 (괴정동)\n10 | 대선약국 | 괴정3동 | 49355 | 부산광역시 사하구 낙동대로 213 (괴정동)\n11 | 유성약국 | 괴정3동 | 49350 | 부산광역시 사하구 낙동대로199번길 3 (괴정동)\n12 | 부영약국 | 괴정4동 | 49399 | 부산광역시 사하구 낙동대로 325, 1층 (괴정동)\n13 | 김기철치과의원 | 당리동 | 49328 | 부산광역시 사하구 낙동대로 398 (당리동)\n14 | 예림기획 | 당리동 | 49328 | 부산광역시 사하구 낙동대로398번길 14 (당리동)\n15 | 어부네코다리 | 당리동 | 49328 | 부산광역시 사하구 낙동대로 394-7, 1층 (당리동)\n16 | 허재영내과의원 | 당리동 | 49323 | 부산광역시 사하구 제석로 54 (당리동)\n17 | (주)영진종합전기 | 하단1동 | 49425 | 부산광역시 사하구 낙동남로 1358 (하단동)\n18 | 가야약국 | 하단1동 | 49430 | 부산광역시 사하구 하신번영로 233, 가락타운 2단지상가 227-107 (하단동)\n19 | 경진이앤지 | 하단1동 | 49409 | 부산광역시 사하구 낙동대로457번길 29 (하단동)\n20 | 박성욱피부과 | 하단1동 | 49427 | 부산광역시 사하구 낙동남로 1424, 6층 (하단동, 동원빌딩)\n21 | 오거리약국 | 하단1동 | 49408 | 부산광역시 사하구 낙동대로 449 (하단동)\n22 | 조경숙가정의학과소아과 | 하단1동 | 49414 | 부산광역시 사하구 하신중앙로 300-1 (하단동)\n23 | 하나로약국 | 하단1동 | 49427 | 부산광역시 사하구 낙동남로 1408 (하단동)\n24 | (주)사오건설 | 하단2동 | 49425 | 부산광역시 사하구 낙동남로 1348-1 (하단동)\n25 | (주)아트몰링 | 하단2동 | 49311 | 부산광역시 사하구 낙동남로 1413, 16층 통합사무소 (하단동, 아트몰링)\n26 | 동아기획 | 하단2동 | 49324 | 부산광역시 사하구 낙동대로 536 (하단동)\n27 | 본가사하점 | 하단2동 | 49301 | 부산광역시 사하구 하신번영로 403, B동 (하단동)\n28 | 제일돌곱창 | 하단2동 | 49308 | 부산광역시 사하구 낙동대로535번길 4 (하단동)\n29 | 대성약국 | 신평1동 | 49442 | 부산광역시 사하구 장평로 298 (신평동)\n30 | 전성업치과의원 | 신평1동 | 49418 | 부산광역시 사하구 장평로 299 (신평동)\n31 | 김사웅내과의원 | 신평2동 | 49431 | 부산광역시 사하구 하신번영로 199  (신평동)\n32 | 박상조소아청소년과의원 | 신평2동 | 49419 | 부산광역시 사하구 하신중앙로 184 (신평동)\n33 | 신익약국 | 신평2동 | 49419 | 부산광역시 사하구 하신중앙로 184 (신평동)\n34 | (주)대영정기 | 장림1동 | 49478 | 부산광역시 사하구 다산로 227 (장림동)\n35 | BJ TECH | 장림1동 | 49478 | 부산광역시 사하구 다산로225번길 45(장림동)\n36 | 부산장림표면처리사업협동조합 | 장림1동 | 49478 | 부산광역시 사하구 다산로 255 (장림동)\n37 | 성진종합상사 | 장림1동 | 49476 | 부산광역시 사하구 하신중앙로 40 (장림동)\n38 | 세화산업 | 장림1동 | 49478 | 부산광역시 사하구 다산로226번길 28 (장림동)\n39 | 우석치과의원 | 장림1동 | 49482 | 부산광역시 사하구 장림번영로 38-1, 4층 (장림동)\n40 | 장림연합의원 | 장림1동 | 49476 | 부산광역시 사하구 하신중앙로22번길 9 (장림동, 만리포빌딩 1층)\n41 | 천호카 | 장림1동 | 49476 | 부산광역시 사하구 하신중앙로 6 (장림동)\n42 | 비앤지1급종합정비 | 장림2동 | 49458 | 부산광역시 사하구 장림로 314 (장림동)\n43 | 이치과의원 | 장림2동 | 49509 | 부산광역시 사하구 다대로 247 (장림동)\n44 | 장약국 | 장림2동 | 49511 | 부산광역시 사하구 다대로 325 (장림동)\n45 | 건강왕약국 | 다대1동 | 49524 | 부산시 사하구 다대로 547, 1층 (다대동, 윤영빌딩)\n46 | 다대치과(손기찬) | 다대1동 | 49494 | 부산광역시 사하구 다대로 556, 5층 (다대동)\n47 | 라파요양병원 | 다대1동 | 49493 | 부산광역시 사하구 다대로 544, 진요빌딩 3~4층 (다대동)\n48 | 박상희내과의원 | 다대1동 | 49524 | 부산광역시 사하구 다대로 555 (다대동)\n49 | 백두봉삼계탕(양명화) | 다대1동 | 49505 | 부산광역시 사하구 다대로 714-1 (다대동)\n50 | 선안요양병원 | 다대1동 | 49503 | 부산광역시 사하구 다대로 616 (다대동)\n51 | 이화약국 | 다대1동 | 49505 | 부산광역시 사하구 다대낙조1길 19 (다대동)\n52 | 도원보쌈 | 다대2동 | 49521 | 부산광역시 사하구 다송로72번길 41 (다대동)\n53 | 캘리포니아치과 | 다대2동 | 49518 | 부산광역시 사하구 다대로429번길 5, 302호 (다대동)\n54 | 구평남해횟집 | 구평동 | 49456 | 부산광역시 사하구 을숙도대로748번길 3 (구평동)\n55 | 부산갈매기식당 | 구평동 | 49454 | 부산광역시 사하구 감천항로 185 (구평동)\n56 | 남해횟집 | 남포동 | 48983 | 부산광역시 중구 자갈치로48번길 3, 자갈치시장(남포동5가)\n57 | (주)큐엔큐 | 화전동 | 46738 | 부산광역시 강서구 화전산단3로 58 (화전동)\n58 | 우리약국 | 거제시 | 53286 | 경상남도 거제시 거제면 읍내로2길 28 (서상리, 거제종합시장)\n59 | 우리동네호두과자 | 당리동 | 49328 | 부산광역시 사하구 낙동대로410번길 14, 1층 104호(당리동)\n60 | 연일자동차정비공업사 | 구평동 | 49396 | 부산광역시 사하구 을숙도대로 755번길 1\n61 | 봉구비어(괴정점) | 괴정1동 | 49380 | 부산광역시 사하구 낙동대로 233번길 8\n62 | 최은석치과의원 | 신평2동 | 49431 | 부산광역시 사하구 하신번영로201번길 1 (신평동)\n[시트명] 착한가게-일반, 지정성금\n연번 | 기부자명 | 동명 | 우편번호 | 주소 | 비고 | 후원종료\n1 | GS25괴정뉴코아 | 괴정1동 | 49381 | 부산광역시 사하구 사하로 199-1 (괴정동) | 일반\n2 | 지오공인중개사 | 괴정3동 | 49351 | 부산광역시 사하구 사리로7번길 22 (괴정동)\n3 | 괴정중앙점현대자동차 | 괴정3동 | 49360 | 부산광역시 사하구 사하로 152 (괴정동)\n4 | 한우사랑 | 당리동 | 49328 | 부산광역시 사하구 낙동대로410번길 24 (당리동)\n5 | GS25당리행운점 | 당리동 | 49326 | 부산광역시 사하구 낙동대로450번길 2 (당리동)\n6 | GS25본병원점 | 당리동 | 49326 | 부산광역시 사하구 승학로 8 (당리동)\n7 | GS25가락타운점(최영옥) | 하단1동 | 49428 | 부산광역시 사하구 동매로 9 (하단동)\n8 | GS25하단사하점 | 하단1동 | 49427 | 부산광역시 사하구 하신중앙로 335 (하단동, 화경빌딩)\n9 | 더블루공인중개사무소 | 하단2동 | 49325 | 부산광역시 사하구 낙동대로 484 (하단동)\n10 | 신평점현대자동차 | 신평2동 | 49437 | 부산광역시 사하구 하신중앙로 118 (신평동)\n11 | 리클라인(이연환) | 장림1동 | 49478 | 부산광역시 사하구 다산로226번길 30 (장림동)\n12 | 오토오아시스롯데마트사하점 | 장림1동 | 49472 | 부산광역시 사하구 을숙도대로 610, 3층 (장림동, 롯데마트)\n13 | GS25감천유림점 | 감천1동 | 49445 | 부산광역시 사하구 감천로 46 (감천동)\n14 | 환성물회 | 신평2동 | 49431 | 부산광역시 사하구 하신번영로167번길 26, 2층 (신평동) | 지정\n15 | 장어나라장수마을 | 신평1동 | 49441 | 부산광역시 사하구 다대로142번길 60(신평동) | 지정\n16 | 피자덕 괴정점 | 괴정1동 | 49385 | 부산광역시 사하구 괴정로 230(괴정동) | 지정\n17 | 골드헤어 | 괴정1동 | 49379 | 부산광역시 사하구 장평로450번길 71(괴정동) | 일반\n18 | Midamoa Jewelry | 범천동 | 47365 | 부산광역시 부산진구 범일로142번길 7(범천동) | 일반\n19 | GS25괴정크로바점 | 괴정1동 | 49360 | 부산광역시 사하구 사하로 166   (괴정동)\n20 | 경신브레이크(신평점) | 신평1동 | 49439 | 부산 사하구 을숙도대로 581 (신평동) 신동아정비내 경신브레이크\n21 | 매듭쟁이 단홍 | 감천2동 | 49364 | 부산 사하구 감내1로175번길 101 (감천동) 단홍 1층"
}