{
  "category": "복지정책",
  "subcategory": "자산형성지원사업",
  "title": "자산형성지원사업",
  "url": "https://www.saha.go.kr/portal/contents.do?mId=0501041100",
  "mId": "0501041100",
  "type": "page",
  "content": "생활안정지원\n한부모가족지원\n일본군위안부피해자 지원\n의료급여지원\n의료비지원\n차상위계층 의료급여지원\n양곡할인 사업안내\n긴급복지지원\n일상돌봄서비스\n지역사회서비스 투자사업 안내\n자산형성지원사업\n자산형성지원사업\n사업 의의\n일하는 저소득 가구 및 청년의 자산형성 지원을 통한 자립기반 마련\n사업내용 및 모집일정\n사업내용 및 모집일정의 구 분,희망저축계좌Ⅰ,희망저축계좌Ⅱ,청년내일저축계좌를 나타낸 표\n구분 희망저축계좌Ⅰ 희망저축계좌Ⅱ 청년내일저축계좌\n가입대상\n근로활동 중인\n기준 중위소득  40%이하  생계,의료급여  수급가구\n기준 중위소득  50%이하  주거,교육급여 수급가구 및 차상위 가구\n기준 중위소득  50%이하 만 15세 이상 만 39세 이하 청년  (월 소득 10만원 이상)\n본인저축액\n월 10~50만원\n유지기준\n근로활동 유지, 본인적립금 저축\n소득 상하한  기준 유지\n소득 상한  기준 유지\n소득 상한  기준 유지\n만기  지원조건\n탈수급\n자립역량교육 이수(10시간) + 자금 사용계획서 제출\n근로장려금\n월 30만원\n1년차 월 10만원 2년차 월 20만원 3년차 월 30만원 (‘25년 이전 가입자는  월 10만원 지원)\n월 30만원\n모집일정\n(1차) 3/3 ~ 3/13 (2차) 6/1 ~ 6/15 (3차) 9/1 ~ 9/14 (4차) 11/2 ~ 11/16\n(1차) 2/2 ~ 2/24 (2차) 7/1 ~ 7/27 (3차) 10/1 ~ 10/26\n(1차) 5/4 ~ 5/20\n신청방법\n행정복지센터 내방 신청\n행정복지센터 내방 신청, 복지로( www.bokjiro.go.kr ) 온라인 신청\n※ 상기 모집일정은 보건복지부 일정 및 예산 상황에 따라 달라질 수 있음.\n사업 상세 바로가기\n자산형성포털 홈페이지",
  "attachments": [],
  "search_text": "생활안정지원\n한부모가족지원\n일본군위안부피해자 지원\n의료급여지원\n의료비지원\n차상위계층 의료급여지원\n양곡할인 사업안내\n긴급복지지원\n일상돌봄서비스\n지역사회서비스 투자사업 안내\n자산형성지원사업\n자산형성지원사업\n사업 의의\n일하는 저소득 가구 및 청년의 자산형성 지원을 통한 자립기반 마련\n사업내용 및 모집일정\n사업내용 및 모집일정의 구 분,희망저축계좌Ⅰ,희망저축계좌Ⅱ,청년내일저축계좌를 나타낸 표\n구분 희망저축계좌Ⅰ 희망저축계좌Ⅱ 청년내일저축계좌\n가입대상\n근로활동 중인\n기준 중위소득  40%이하  생계,의료급여  수급가구\n기준 중위소득  50%이하  주거,교육급여 수급가구 및 차상위 가구\n기준 중위소득  50%이하 만 15세 이상 만 39세 이하 청년  (월 소득 10만원 이상)\n본인저축액\n월 10~50만원\n유지기준\n근로활동 유지, 본인적립금 저축\n소득 상하한  기준 유지\n소득 상한  기준 유지\n소득 상한  기준 유지\n만기  지원조건\n탈수급\n자립역량교육 이수(10시간) + 자금 사용계획서 제출\n근로장려금\n월 30만원\n1년차 월 10만원 2년차 월 20만원 3년차 월 30만원 (‘25년 이전 가입자는  월 10만원 지원)\n월 30만원\n모집일정\n(1차) 3/3 ~ 3/13 (2차) 6/1 ~ 6/15 (3차) 9/1 ~ 9/14 (4차) 11/2 ~ 11/16\n(1차) 2/2 ~ 2/24 (2차) 7/1 ~ 7/27 (3차) 10/1 ~ 10/26\n(1차) 5/4 ~ 5/20\n신청방법\n행정복지센터 내방 신청\n행정복지센터 내방 신청, 복지로( www.bokjiro.go.kr ) 온라인 신청\n※ 상기 모집일정은 보건복지부 일정 및 예산 상황에 따라 달라질 수 있음.\n사업 상세 바로가기\n자산형성포털 홈페이지"
}