{
  "category": "세무민원안내",
  "subcategory": "취득세",
  "title": "취득세",
  "url": "https://www.saha.go.kr/portal/contents.do?mId=0105020400",
  "mId": "0105020400",
  "type": "page",
  "content": "지방세종류 및 내용\n재산세\n등록면허세\n지방소득세\n취득세\n주민세\n자동차세\n지역자원시설세\n지방교육세\n취득세\n취득세는 과세 대상에 대한 매매,교환, 상속,증여, 기부, 법인에 대한 현물출자, 건축물 신축, 증축, 시설물 개수, 공유수면의 매립, 간척에 의한 토지 조성 등 유·무상 취득은 물론 토지의 지목변경, 차량·기계장비·선박의 종류변경, 과점주주의 간주취득 등에 부과하는 보통세로 취득한 날로부터 60일 이내에 과세물건지 관할구청에 가서 신고하고 산출된 세액을 납부하여야 하며, 그러하지 아니하면 가산세를 추가 부담하여야 합니다.\n납세의무자 :\n부동산, 차량, 선박 등의 과세대상 물건을 취득한 자는 취득세를 납부할 의무가 있습니다.\n과세대상 :\n부동산, 차량, 기계장비, 항공기, 선박, 임목, 골프회원권, 콘도미니엄회원권, 종합체육시설이용회원권 등이 있습니다.\n과세표준 :\n원칙 : 취득당시의 가액\n무상취득\n원칙 : 시가인정액 (상속 제외)\n예외 : 시가표준액\n유상취득 (부동산등 승계) : 사실상의 취득가격\n원시취득 (신축, 증축 등)\n원칙 : 사실상의 취득가격\n예외 : 시가표준액\n세 율 :\n상속 : 2.8％\n무상취득 : 3.5%\n원시취득 : 2.8%\n일반세율 : 4%\n주택에 대한 취득세\n6억원 이하 주택 : 1%\n6억원 초과 9억원 이하 주택 : 다음 계산식에 따라 산출한 세율. 이 경우 소수점이하 다섯째자리에서 반올림하여 소수점 넷째자리까지 계산한다.\n9억원 초과 주택 : 3%\n중과세\n고급주택·고급오락장·골프장 등 : 12%\n법인 등 의 주택취득 : 12%\n1세대 3주택 이상에 해당하는 주택으로서 조정대상지역에 있는 주택 취득 : 12%\n1세대 2주택에 해당하는 주택으로서 조정대상지역에 있는 주택 취득 : 8%\n1세대 3주택에 해당하는 주택으로서 조정대상지역 외의 지역에 있는 주택 취득 : 8%\n1세대 4주택 이상에 해당하는 주택으로서 조정대상지역 외의 지역에 있는 주택 취득 : 12%\n신고 및 납부기한\n일반 : 취득일로부터 60일 이내\n무상취득 : 취득일이 속하는 달의 말일부터 3개월 이내\n상속 : 상속개시일이 속하는 달의 말일부터 6개월 이내\n보통징수 : 미신고ㆍ미납부자에 대해 고지(무신고가산세 : 100분의 20, 납부지연가산세 : 지연일수 X 1십만분의 22)",
  "attachments": [],
  "search_text": "지방세종류 및 내용\n재산세\n등록면허세\n지방소득세\n취득세\n주민세\n자동차세\n지역자원시설세\n지방교육세\n취득세\n취득세는 과세 대상에 대한 매매,교환, 상속,증여, 기부, 법인에 대한 현물출자, 건축물 신축, 증축, 시설물 개수, 공유수면의 매립, 간척에 의한 토지 조성 등 유·무상 취득은 물론 토지의 지목변경, 차량·기계장비·선박의 종류변경, 과점주주의 간주취득 등에 부과하는 보통세로 취득한 날로부터 60일 이내에 과세물건지 관할구청에 가서 신고하고 산출된 세액을 납부하여야 하며, 그러하지 아니하면 가산세를 추가 부담하여야 합니다.\n납세의무자 :\n부동산, 차량, 선박 등의 과세대상 물건을 취득한 자는 취득세를 납부할 의무가 있습니다.\n과세대상 :\n부동산, 차량, 기계장비, 항공기, 선박, 임목, 골프회원권, 콘도미니엄회원권, 종합체육시설이용회원권 등이 있습니다.\n과세표준 :\n원칙 : 취득당시의 가액\n무상취득\n원칙 : 시가인정액 (상속 제외)\n예외 : 시가표준액\n유상취득 (부동산등 승계) : 사실상의 취득가격\n원시취득 (신축, 증축 등)\n원칙 : 사실상의 취득가격\n예외 : 시가표준액\n세 율 :\n상속 : 2.8％\n무상취득 : 3.5%\n원시취득 : 2.8%\n일반세율 : 4%\n주택에 대한 취득세\n6억원 이하 주택 : 1%\n6억원 초과 9억원 이하 주택 : 다음 계산식에 따라 산출한 세율. 이 경우 소수점이하 다섯째자리에서 반올림하여 소수점 넷째자리까지 계산한다.\n9억원 초과 주택 : 3%\n중과세\n고급주택·고급오락장·골프장 등 : 12%\n법인 등 의 주택취득 : 12%\n1세대 3주택 이상에 해당하는 주택으로서 조정대상지역에 있는 주택 취득 : 12%\n1세대 2주택에 해당하는 주택으로서 조정대상지역에 있는 주택 취득 : 8%\n1세대 3주택에 해당하는 주택으로서 조정대상지역 외의 지역에 있는 주택 취득 : 8%\n1세대 4주택 이상에 해당하는 주택으로서 조정대상지역 외의 지역에 있는 주택 취득 : 12%\n신고 및 납부기한\n일반 : 취득일로부터 60일 이내\n무상취득 : 취득일이 속하는 달의 말일부터 3개월 이내\n상속 : 상속개시일이 속하는 달의 말일부터 6개월 이내\n보통징수 : 미신고ㆍ미납부자에 대해 고지(무신고가산세 : 100분의 20, 납부지연가산세 : 지연일수 X 1십만분의 22)"
}